BMI_cal.py
main.py
BMI_Test/BMI_cal.py
BMI_Test/main.py
BMI_Test-0.0.0.1.dist-info/METADATA
BMI_Test-0.0.0.1.dist-info/WHEEL
BMI_Test-0.0.0.1.dist-info/top_level.txt
BMI_Test-0.0.0.1.dist-info/RECORD
