Metadata-Version: 2.1
Name: BMI-Test
Version: 0.0.0.1
Summary: My Second Test Package
Home-page: UNKNOWN
Author: Karl Lee
Author-email: chiwon2005@gmail.com
License: MIT
Platform: UNKNOWN
Requires-Python: >=3
